synthesizer/__init__.py
synthesizer/player.py
synthesizer/synthesizer.py
synthesizer/writer.py
synthesizer-0.1.4.dist-info/DESCRIPTION.rst
synthesizer-0.1.4.dist-info/METADATA
synthesizer-0.1.4.dist-info/RECORD
synthesizer-0.1.4.dist-info/WHEEL
synthesizer-0.1.4.dist-info/metadata.json
synthesizer-0.1.4.dist-info/top_level.txt
synthesizer-0.1.4.dist-info/zip-safe
