Metadata-Version: 2.0
Name: synthesizer
Version: 0.1.4
Summary: A simple virtual analog synthesizer.
Home-page: https://github.com/yuma-m/synthesizer
Author: Yuma Mihira
Author-email: info@yurax2.com
License: GPLv3
Keywords: analog synthesizer
Platform: UNKNOWN
Classifier: Development Status :: 3 - Alpha
Classifier: License :: OSI Approved :: GNU General Public License v3 (GPLv3)
Classifier: Operating System :: MacOS :: MacOS X
Classifier: Operating System :: POSIX :: Linux
Classifier: Topic :: Multimedia :: Sound/Audio :: MIDI
Classifier: Topic :: Multimedia :: Sound/Audio :: Sound Synthesis
Requires-Dist: enum34 (>=1.1.6)
Requires-Dist: numpy (>=1.13.3)
Requires-Dist: scipy (>=0.19.1)
